scrapper/__init__.py
scrapper/webscrapper.py
web_scrapper_embrapa-0.1.0.dist-info/licenses/LICENSE.txt
web_scrapper_embrapa-0.1.0.dist-info/METADATA
web_scrapper_embrapa-0.1.0.dist-info/WHEEL
web_scrapper_embrapa-0.1.0.dist-info/top_level.txt
web_scrapper_embrapa-0.1.0.dist-info/RECORD
